stactools/naip/__init__.py
stactools/naip/commands.py
stactools/naip/constants.py
stactools/naip/stac.py
stactools/naip/utils.py
stactools_naip-0.5.0.dist-info/LICENSE
stactools_naip-0.5.0.dist-info/METADATA
stactools_naip-0.5.0.dist-info/WHEEL
stactools_naip-0.5.0.dist-info/top_level.txt
stactools_naip-0.5.0.dist-info/RECORD
