Metadata-Version: 2.1
Name: stactools-naip
Version: 0.5.0
Summary: STAC item creation tools for NAIP dataset.
Author-email: stac-utils <stac@radiant.earth>
Project-URL: homepage, https://github.com/stactools-naips/stactools-naip
Project-URL: documentation, https://stactools-naip.readthedocs.io/en/latest/
Keywords: stactools,pystac,catalog,STAC
Classifier: Development Status :: 4 - Beta
Classifier: License :: OSI Approved :: Apache Software License
Classifier: Programming Language :: Python :: 3.8
Classifier: Programming Language :: Python :: 3.9
Classifier: Programming Language :: Python :: 3.10
Classifier: Programming Language :: Python :: 3.11
Requires-Python: >=3.8
License-File: LICENSE
Requires-Dist: stactools >=0.4.3
Requires-Dist: pystac >=1.5
Provides-Extra: dev
Requires-Dist: black ~=23.3 ; extra == 'dev'
Requires-Dist: codespell ~=2.2 ; extra == 'dev'
Requires-Dist: coverage ~=7.4.0 ; extra == 'dev'
Requires-Dist: pre-commit ~=3.3 ; extra == 'dev'
Requires-Dist: flake8 ~=7.0.0 ; extra == 'dev'
Requires-Dist: pytest-cov ~=3.0 ; extra == 'dev'
Requires-Dist: pytest ~=7.3 ; extra == 'dev'
